{
  "white_orchard": {
    "name": "White Orchard",
    "place_description": "White Orchard is a region and village located in Temeria famous for its fruit orchards, whose boughs burst out white blossoms come spring. The Ismena river flows through the village and continues north.",
    "badge": "./images/white-orchard-badge.png",
    "contracts": [
      {
        "questId": 1,
        "contract_name": "Beast of White Orchard",
        "monster_id": "griffin",
        "monster_quantity": 1,
        "reward": 500,
        "exp": 200,
        "short_description": "A griffin has been terrorizing the fields near the Ismena River.",
        "description": "A Griffin has made its nest near the fields south of the Ismena River. It has been preying on livestock and even attacked a patrol. Villagers are offering a handsome reward for slaying the beast and bringing proof of the kill.",
        "isCompleted": false
      },
      {
        "questId": 2,
        "contract_name": "Drowners by the Old Mill",
        "monster_id": "drowner",
        "monster_quantity": 3,
        "reward": 200,
        "exp": 80,
        "short_description": "Drowners lurking near the old mill are scaring the fishermen away.",
        "description": "Several drowners have been sighted along the riverbank near the old mill. Fishermen fear to go near the water after dusk. The village elder seeks someone skilled enough to cleanse the area of the monsters.",
        "isCompleted": false
      },
      {
        "questId": 3,
        "contract_name": "Song Beneath the River",
        "monster_id": "siren",
        "monster_quantity": 3,
        "reward": 400,
        "exp": 100,
        "short_description": "Sailors report eerie songs luring them toward the river cliffs.",
        "description": "Sailors traveling the Ismena River report eerie singing that lures them toward the rocks at night. Those who follow never return. The locals suspect a group of sirens nesting near the river cliffs. A reward is offered for their heads.",
        "isCompleted": false
      },
      {
        "questId": 4,
        "contract_name": "Devil by the well",
        "monster_id": "devil-by-the-well",
        "monster_quantity": 1,
        "reward": 300,
        "exp": 100,
        "short_description": "Villagers of the Abandoned Village claim a vengeful spirit haunts the old well, dragging the living to their deaths",
        "description": "Villagers report a restless spirit by the old well. It attacks anyone who ventures too close. The elders promise a reward for lifting the curse. None dare fetch water or till the nearby fields, for the ghost's wailing is heard at dawn and dusk. Any witcher brave enough to face the spirit shall be paid 300 crowns upon proof of the wraith’s defeat."
      }
    ],
    "sub_locations": {
      "woesong_bridge": {
        "name": "Woesong Bridge 🌉",
        "monsters_found": ["drowner", "nekker"],
        "merchant": null,
        "blacksmith": null,
        "armorer": { "name": "Woesong Armorer", "items_in_stock": [] },
        "resources_to_gather": ["herbs", "river_clay"]
      },
      "nilfgaardian_garrison": {
        "name": "Nilfgaardian Garrison ⚔️",
        "monsters_found": null,
        "merchant": null,
        "blacksmith": null,
        "armorer": null,
        "resources_to_gather": ["metal_scrap", "wolf_hide"]
      },
      "abandoned_village": {
        "name": "Abandoned Village 🏚️",
        "monsters_found": ["ghoul", "noonwraith", "alghoul"],
        "merchant": null,
        "blacksmith": null,
        "armorer": null,
        "resources_to_gather": ["herbs", "bones"]
      },
      "sawmill": {
        "name": "Sawmill 🪵",
        "monsters_found": ["wolf", "drowner"],
        "merchant": null,
        "blacksmith": null,
        "armorer": null,
        "resources_to_gather": ["timber", "wolf_pelt"]
      },
      "broken_cart_pass": {
        "name": "Broken Cart Pass 🛞",
        "monsters_found": ["bandit", "nekker"],
        "merchant": null,
        "blacksmith": null,
        "armorer": null,
        "resources_to_gather": ["loot_crates", "herbs"]
      },
      "isemen_riverbank": {
        "name": "Isemen Riverbank 🌊",
        "monsters_found": ["drowner", "siren", "nekker"],
        "merchant": null,
        "blacksmith": null,
        "armorer": null,
        "resources_to_gather": ["water_essence", "reeds"]
      },
      "crossroads_inn": {
        "name": "Crossroads Inn 🍺",
        "monsters_found": null,
        "merchant": { "name": "Crossroads Merchant", "items_in_stock": [] },
        "blacksmith": null,
        "armorer": null,
        "resources_to_gather": null
      },
      "hunter_cabin": {
        "name": "Hunter's Cabin 🐺",
        "monsters_found": ["wolf", "bandit"],
        "merchant": null,
        "blacksmith": null,
        "armorer": null,
        "resources_to_gather": ["animal_hide", "herbs"]
      },
      "orchard_fields": {
        "name": "Orchard Fields 🍎",
        "monsters_found": ["griffin", "harpy"],
        "merchant": null,
        "blacksmith": null,
        "armorer": null,
        "resources_to_gather": ["fruit", "herbs"]
      },
      "sawmill_forest_edge": {
        "name": "Sawmill Forest Edge 🌲",
        "monsters_found": ["wolf", "nekker"],
        "merchant": null,
        "blacksmith": null,
        "armorer": null,
        "resources_to_gather": ["wood", "herbs"]
      }
    },
    "default_sub_location": "woesong_bridge"
  },
  "velen": {
    "name": "Velen",
    "place_description": "A war-torn, swampy region south of Novigrad with ruined villages, bogs and bandit-filled roads. Velen is harsh and populated by desperate folk and dangerous beasts.",
    "badge": "./images/velen-badge.png",
    "contracts": [
      {
        "questId": 101,
        "contract_name": "Leshen in Crookback Bog",
        "monster_id": "leshen",
        "monster_quantity": 1,
        "reward": 900,
        "exp": 400,
        "short_description": "A Leshen has been seen drawing beasts to trample the peat bogs.",
        "description": "Locals report an ancient Leshen has returned and is calling animals and roots to protect its domain. Pack animal routes have been destroyed and the farmers fear for their livestock.",
        "isCompleted": false
      },
      {
        "questId": 102,
        "contract_name": "Wyvern Nest at Crow's Perch",
        "monster_id": "wyvern",
        "monster_quantity": 1,
        "reward": 600,
        "exp": 300,
        "short_description": "A wyvern nesting in the high cliffs has started raiding nearby farms.",
        "description": "Farmers report missing livestock and a large, dragon-like shadow seen circling the cliffs near Crow's Perch. Bring proof of the wyvern's defeat.",
        "isCompleted": false
      }
    ],
    "sub_locations": {
      "crookback_bog": {
        "name": "Crookback Bog 🌫️",
        "monsters_found": ["leshen", "nekker"],
        "merchant": null,
        "blacksmith": null,
        "armorer": null,
        "resources_to_gather": ["herbs", "leshen_root"]
      },
      "crow_perch_cliffs": {
        "name": "Crow's Perch Cliffs 🪶",
        "monsters_found": ["wyvern"],
        "merchant": null,
        "blacksmith": null,
        "armorer": null
      },
      "dirtroad_crossing": {
        "name": "Dirtroad Crossing 🪔",
        "monsters_found": ["bandit", "wolf"],
        "merchant": { "name": "Traveling Merchant", "items_in_stock": [] },
        "blacksmith": null,
        "armorer": null
      },
      "orcchard_swamp": {
        "name": "Orchard Swamp 🐸",
        "monsters_found": ["drowner", "foglet", "nekker"],
        "merchant": null,
        "blacksmith": null,
        "armorer": null,
        "resources_to_gather": ["swamp_herbs", "reed_fibers"]
      },
      "ruined_watchtower": {
        "name": "Ruined Watchtower 🏰",
        "monsters_found": ["ghoul", "wraith", "alghoul"],
        "merchant": null,
        "blacksmith": null,
        "armorer": null,
        "resources_to_gather": ["ancient_bricks", "rune_dust"]
      },
      "blackbough_village": {
        "name": "Blackbough Village 🌾",
        "monsters_found": null,
        "merchant": null,
        "blacksmith": { "name": "Blackbough Blacksmith", "items_in_stock": ["steel_sword_basic"] },
        "armorer": null,
        "resources_to_gather": ["grain", "herbs"]
      },
      "hanged_mans_tree": {
        "name": "Hanged Man's Tree ⚰️",
        "monsters_found": ["wraith", "ghoul"],
        "merchant": null,
        "blacksmith": null,
        "armorer": null,
        "resources_to_gather": ["bones", "spirit_essence"]
      },
      "mulbrydale": {
        "name": "Mulbrydale 🕯️",
        "monsters_found": ["bandit"],
        "merchant": { "name": "Mulbrydale Innkeeper", "items_in_stock": [] },
        "blacksmith": null,
        "armorer": null,
        "resources_to_gather": ["herbs", "boar_hide"]
      },
      "lornruk_lighthouse": {
        "name": "Lornruk Lighthouse 🏝️",
        "monsters_found": ["harpy", "siren"],
        "merchant": null,
        "blacksmith": null,
        "armorer": null,
        "resources_to_gather": ["seashells", "draconid_blood"]
      },
      "devil_pit": {
        "name": "Devil's Pit 🔥",
        "monsters_found": ["ghoul", "alghoul"],
        "merchant": null,
        "blacksmith": null,
        "armorer": null,
        "resources_to_gather": ["ore_fragments", "bone_shards"]
      },
      "reardon_manor": {
        "name": "Reardon Manor 🏚️",
        "monsters_found": ["noonwraith"],
        "merchant": null,
        "blacksmith": null,
        "armorer": null,
        "resources_to_gather": ["silver_candlestick", "linen"]
      },
      "burned_hamlet": {
        "name": "Burned Hamlet 🪓",
        "monsters_found": ["bandit"],
        "merchant": null,
        "blacksmith": null,
        "armorer": null,
        "resources_to_gather": ["charcoal", "metal_scrap"]
      }
    },
    "default_sub_location": "crow_perch_cliffs"
  },
  "novigrad": {
    "name": "Novigrad",
    "place_description": "A bustling free city and merchant hub. Novigrad is rife with intrigue, markets, churches and criminal networks — monsters hide in alleys and sewers.",
    "badge": "./images/novigrad-badge.png",
    "contracts": [
      {
        "questId": 201,
        "contract_name": "Sewer Beast",
        "monster_id": "nekker",
        "monster_quantity": 5,
        "reward": 300,
        "exp": 120,
        "short_description": "Creatures have taken up residence in the old Novigrad sewers.",
        "description": "Sewer workers unearthed signs of small, aggressive beasts living beneath Novigrad. Civilians have seen shadowy figures near the drains at night.",
        "isCompleted": false
      }
    ],
    "sub_locations": {
      "docks": {
        "name": "Novigrad Docks",
        "monsters_found": ["siren", "drowner"],
        "merchant": { "name": "Dockmaster", "items_in_stock": [] },
        "blacksmith": null,
        "armorer": null,
        "resources_to_gather": ["fish_oil", "reeds"]
      },
      "old_sewers": {
        "name": "Old Sewers",
        "monsters_found": ["nekker"],
        "merchant": null,
        "blacksmith": null,
        "armorer": null
      },
      "market_square": {
        "name": "Market Square",
        "monsters_found": null,
        "merchant": { "name": "Market Merchants", "items_in_stock": [] },
        "blacksmith": null,
        "armorer": null
      }
    },
    "default_sub_location": "docks"
  },
  "skellige": {
    "name": "Skellige",
    "place_description": "A brutal archipelago of windswept isles, famed for warriors, longships and rugged landscape. Sea-monsters and savage beasts make the islands perilous.",
    "badge": "./images/skellige-badge.png",
    "contracts": [
      {
        "questId": 301,
        "contract_name": "Waves of the Wyvern",
        "monster_id": "wyvern",
        "monster_quantity": 1,
        "reward": 700,
        "exp": 320,
        "short_description": "A wyvern has nested near a coastal village and attacks passing ships.",
        "description": "Villagers report a fierce wyvern nesting atop a coastal stack, swooping down to plunder ships and livestock. The chieftain offers coin for its head.",
        "isCompleted": false
      },
      {
        "questId": 302,
        "contract_name": "Spirits of the Standing Stones",
        "monster_id": "noonwraith",
        "monster_quantity": 1,
        "reward": 500,
        "exp": 220,
        "short_description": "A restless specter haunts the ancient standing stones.",
        "description": "Islanders whisper of a noonwraith that appears near the old standing stones. Farmers report terrified cattle and a chilling wail at midday.",
        "isCompleted": false
      }
    ],
    "sub_locations": {
      "harral_west": {
        "name": "Harral West",
        "monsters_found": ["wyvern", "nekker"],
        "resources_to_gather": ["fish_oil", "wyvern_scale"]
      },
      "standing_stones": {
        "name": "Ancient Standing Stones",
        "monsters_found": ["noonwraith"],
        "merchant": null,
        "blacksmith": null,
        "armorer": null
      },
      "longship_harbor": {
        "name": "Longship Harbor",
        "monsters_found": ["siren"],
        "merchant": { "name": "Harbor Merchant", "items_in_stock": [] },
        "blacksmith": null,
        "armorer": null
      },
      "kaer_torlde": {
        "name": "Kaer Torlde",
        "monsters_found": null,
        "merchant": null,
        "blacksmith": null,
        "armorer": null
      }
    },
    "default_sub_location": "kaer_torlde"
  }
}
